digital_ocean_dynamic_dns/__init__.py
digital_ocean_dynamic_dns/api_key_helpers.py
digital_ocean_dynamic_dns/args.py
digital_ocean_dynamic_dns/constants.py
digital_ocean_dynamic_dns/database.py
digital_ocean_dynamic_dns/ddns.py
digital_ocean_dynamic_dns/do_api.py
digital_ocean_dynamic_dns/domains.py
digital_ocean_dynamic_dns/exceptions.py
digital_ocean_dynamic_dns/info.py
digital_ocean_dynamic_dns/ip.py
digital_ocean_dynamic_dns/logs.py
digital_ocean_dynamic_dns/manage.py
digital_ocean_dynamic_dns/subdomains.py
digital_ocean_dynamic_dns-1.3.7.dist-info/LICENSE
digital_ocean_dynamic_dns-1.3.7.dist-info/METADATA
digital_ocean_dynamic_dns-1.3.7.dist-info/WHEEL
digital_ocean_dynamic_dns-1.3.7.dist-info/entry_points.txt
digital_ocean_dynamic_dns-1.3.7.dist-info/top_level.txt
digital_ocean_dynamic_dns-1.3.7.dist-info/RECORD
