Metadata-Version: 2.1
Name: digital-ocean-dynamic-dns
Version: 1.3.7
Summary: Python-based CLI tool for managing dynamic dns with Digital Ocean.
Author-email: Tyler Nivin <tyler@nivin.tech>
Project-URL: Repository, https://github.com/nivintw/ddns
Project-URL: Issues, https://github.com/nivintw/ddns/issues
Classifier: Development Status :: 3 - Alpha
Classifier: Intended Audience :: Developers
Classifier: Intended Audience :: Information Technology
Classifier: License :: OSI Approved :: MIT License
Classifier: Programming Language :: Python :: 3
Classifier: Programming Language :: Python :: 3.12
Classifier: Topic :: Internet
Classifier: Topic :: System :: Networking
Classifier: Topic :: System :: Systems Administration
Classifier: Topic :: Utilities
Requires-Python: >=3.12
License-File: LICENSE
Requires-Dist: rich >=13.8.0
Requires-Dist: requests >=2.32.3
Requires-Dist: more-itertools >=10.4.0
